automata/__init__.py
automata/py.typed
automata/base/__init__.py
automata/base/animation.py
automata/base/automaton.py
automata/base/config.py
automata/base/exceptions.py
automata/base/utils.py
automata/fa/__init__.py
automata/fa/animation.py
automata/fa/dfa.py
automata/fa/fa.py
automata/fa/gnfa.py
automata/fa/nfa.py
automata/pda/__init__.py
automata/pda/configuration.py
automata/pda/dpda.py
automata/pda/exceptions.py
automata/pda/npda.py
automata/pda/pda.py
automata/pda/stack.py
automata/regex/__init__.py
automata/regex/lexer.py
automata/regex/parser.py
automata/regex/postfix.py
automata/regex/regex.py
automata/tm/__init__.py
automata/tm/configuration.py
automata/tm/dtm.py
automata/tm/exceptions.py
automata/tm/mntm.py
automata/tm/ntm.py
automata/tm/tape.py
automata/tm/tm.py
automata/tm/tools.py
automata_lib-9.1.2.dist-info/licenses/LICENSE.txt
automata_lib-9.1.2.dist-info/METADATA
automata_lib-9.1.2.dist-info/WHEEL
automata_lib-9.1.2.dist-info/top_level.txt
automata_lib-9.1.2.dist-info/RECORD
