Metadata-Version: 2.4
Name: automata-lib
Version: 9.1.2
Summary: A Python library for simulating finite automata, pushdown automata, and Turing machines
Author-email: Caleb Evans <caleb@calebevans.me>
Maintainer-email: Caleb Evans <caleb@calebevans.me>, "Eliot W. Robson" <eliot.robson24@gmail.com>
License-Expression: MIT
Project-URL: homepage, https://github.com/caleb531/automata
Project-URL: documentation, https://caleb531.github.io/automata/
Project-URL: repository, https://github.com/caleb531/automata
Project-URL: changelog, https://github.com/caleb531/automata/releases
Keywords: automata,finite,non-deterministic,pushdown,turing,machine,state
Classifier: Development Status :: 5 - Production/Stable
Classifier: Programming Language :: Python :: 3.9
Classifier: Programming Language :: Python :: 3.10
Classifier: Programming Language :: Python :: 3.11
Classifier: Programming Language :: Python :: 3.12
Classifier: Programming Language :: Python :: 3.13
Classifier: Topic :: Scientific/Engineering :: Mathematics
Classifier: Intended Audience :: Education
Classifier: Intended Audience :: Science/Research
Requires-Python: >=3.9
License-File: LICENSE.txt
Requires-Dist: networkx>=2.6.2
Requires-Dist: frozendict>=2.3.4
Requires-Dist: typing-extensions>=4.5.0
Requires-Dist: cached_method>=0.1.0
Provides-Extra: visual
Requires-Dist: coloraide>=1.8.2; extra == "visual"
Requires-Dist: manim>=0.19.0; extra == "visual"
Requires-Dist: pygraphviz>=1.10; extra == "visual"
Dynamic: license-file
